{"v":4,"entries":{"example-introduction--docs":{"id":"example-introduction--docs","title":"Example/Introduction","name":"Docs","importPath":"./src/stories/Introduction.mdx","storiesImports":[],"type":"docs","tags":["unattached-mdx","docs"]},"card-news-maldives--maldives":{"id":"card-news-maldives--maldives","title":"Card/News/Maldives","name":"Maldives","importPath":"./src/card-news-maldives/CardNewsMaldives.stories.tsx","tags":["story"],"type":"story"},"card-news-spa--spa":{"id":"card-news-spa--spa","title":"Card/News/Spa","name":"Spa","importPath":"./src/card-travel-spa/CardNewsSpa.stories.tsx","tags":["story"],"type":"story"},"card-news-spa--spa-cover":{"id":"card-news-spa--spa-cover","title":"Card/News/Spa","name":"Spa Cover","importPath":"./src/card-travel-spa/CardNewsSpa.stories.tsx","tags":["story"],"type":"story"}}}
